pkgmngr/__init__.py
pkgmngr/__main__.py
pkgmngr/common/__init__.py
pkgmngr/common/cli.py
pkgmngr/common/config.py
pkgmngr/common/errors.py
pkgmngr/common/pypi.py
pkgmngr/common/templates.py
pkgmngr/common/utils.py
pkgmngr/lifecycle/__init__.py
pkgmngr/lifecycle/cli.py
pkgmngr/lifecycle/create.py
pkgmngr/lifecycle/github.py
pkgmngr/lifecycle/pypi.py
pkgmngr/lifecycle/rename.py
pkgmngr/lifecycle/replace.py
pkgmngr/lifecycle/repo.py
pkgmngr/lifecycle/update.py
pkgmngr/lifecycle/wrap.py
pkgmngr/snapshot/__init__.py
pkgmngr/snapshot/cli.py
pkgmngr/snapshot/restore.py
pkgmngr/snapshot/snapshot.py
pkgmngr/snapshot/utils.py
pkgmngr/templates/__init__.py
pkgmngr/templates/gitignore.txt
pkgmngr/templates/init_py.txt
pkgmngr/templates/license_mit.txt
pkgmngr/templates/main_py.txt
pkgmngr/templates/manifest_in.txt
pkgmngr/templates/pyproject_toml.txt
pkgmngr/templates/readme.txt
pkgmngr/templates/run_tests_py.txt
pkgmngr/templates/setup_py.txt
pkgmngr/templates/test_py.txt
tests/__init__.py
tests/conftest.py
tests/run_tests.py
tests/test_common_utils.py
tests/test_create.py
tests/test_github_integration.py
tests/test_rename.py
tests/test_replace.py
tests/test_restore.py
tests/test_snapshot.py
tests/test_update.py
tests/test_wrap.py
pkgmngr-0.1.8.dist-info/LICENSE
pkgmngr-0.1.8.dist-info/METADATA
pkgmngr-0.1.8.dist-info/WHEEL
pkgmngr-0.1.8.dist-info/entry_points.txt
pkgmngr-0.1.8.dist-info/top_level.txt
pkgmngr-0.1.8.dist-info/RECORD
