Metadata-Version: 2.2
Name: pkgmngr
Version: 0.1.8
Summary: Comprehensive Python package utilities for creation, snapshotting, and lifecycle management
Home-page: https://github.com/B4PT0R/pkgmngr
Author: Baptiste FERRAND
Author-email: bferrand.maths@gmail.com
Project-URL: Bug Reports, https://github.com/B4PT0R/pkgmngr/issues
Project-URL: Source, https://github.com/B4PT0R/pkgmngr
Project-URL: Documentation, https://github.com/B4PT0R/pkgmngr#readme
Keywords: package,utilities,snapshot,backup,restore,versioning,creation,github,lifecycle,documentation,python-package
Classifier: Programming Language :: Python :: 3
Classifier: Programming Language :: Python :: 3.6
Classifier: Programming Language :: Python :: 3.7
Classifier: Programming Language :: Python :: 3.8
Classifier: Programming Language :: Python :: 3.9
Classifier: Programming Language :: Python :: 3.10
Classifier: Programming Language :: Python :: 3.11
Classifier: License :: OSI Approved :: MIT License
Classifier: Operating System :: OS Independent
Classifier: Development Status :: 4 - Beta
Classifier: Intended Audience :: Developers
Classifier: Topic :: Software Development :: Libraries :: Python Modules
Classifier: Topic :: Software Development :: Version Control :: Git
Classifier: Topic :: Software Development :: Documentation
Requires-Python: >=3.6
License-File: LICENSE
Requires-Dist: requests>=2.25.0
Requires-Dist: toml>=0.10.2
Requires-Dist: pathspec>=0.9.0
Provides-Extra: dev
Requires-Dist: pytest>=6.0.0; extra == "dev"
Requires-Dist: pytest-cov>=2.12.0; extra == "dev"
Requires-Dist: flake8>=3.9.0; extra == "dev"
Requires-Dist: black>=21.5b2; extra == "dev"
Requires-Dist: coverage>=5.5; extra == "dev"
Requires-Dist: build>=0.7.0; extra == "dev"
Requires-Dist: twine>=3.4.1; extra == "dev"
Requires-Dist: isort>=5.9.1; extra == "dev"
Dynamic: author
Dynamic: author-email
Dynamic: classifier
Dynamic: description
Dynamic: description-content-type
Dynamic: home-page
Dynamic: keywords
Dynamic: project-url
Dynamic: provides-extra
Dynamic: requires-dist
Dynamic: requires-python
Dynamic: summary
